LICENSE.txt
README.md
setup.cfg
setup.py
robinhood_crypto_trader/__init__.py
robinhood_crypto_trader.egg-info/PKG-INFO
robinhood_crypto_trader.egg-info/SOURCES.txt
robinhood_crypto_trader.egg-info/dependency_links.txt
robinhood_crypto_trader.egg-info/requires.txt
robinhood_crypto_trader.egg-info/top_level.txt
robinhood_crypto_trader/crypto_trader/__init__.py
robinhood_crypto_trader/crypto_trader/order.py
robinhood_crypto_trader/crypto_trader/trader.py
tests/__init__.py
tests/test.py